bayesfm/__init__.py
bayesfm/bfm.py
bayesfm/example_data.py
bayesfm-0.2.2.dist-info/LICENSE
bayesfm-0.2.2.dist-info/METADATA
bayesfm-0.2.2.dist-info/WHEEL
bayesfm-0.2.2.dist-info/top_level.txt
bayesfm-0.2.2.dist-info/RECORD
