Metadata-Version: 2.1
Name: bayesfm
Version: 0.2.2
Summary: Bayesian Fama-MacBeth Regressions
Author: Svetlana Bryzgalova, Jiantao Huang, Christian Julliard
Maintainer: Gustavo Amarante
Maintainer-email: developer@dsgepy.com
Keywords: asset pricing,factor models,risk premia,bayesian methods
License-File: LICENSE
Requires-Dist: pandas
Requires-Dist: scipy
Requires-Dist: numpy
Requires-Dist: matplotlib
